chrome_dev/__init__.py
chrome_dev/chrome_dev.py
tachibind/__init__.py
tachibind/cli.py
tachibind/per_chapter_dl.py
tachibind-0.1.0.dist-info/licenses/LICENSE
tachibind-0.1.0.dist-info/METADATA
tachibind-0.1.0.dist-info/WHEEL
tachibind-0.1.0.dist-info/entry_points.txt
tachibind-0.1.0.dist-info/top_level.txt
tachibind-0.1.0.dist-info/RECORD
