Metadata-Version: 2.4
Name: tachibind
Version: 0.1.0
Summary: CLI to fetch manga chapters and export one PDF per chapter (Kindle-friendly).
Author-email: Aryaman Saini <83552832+ary5@users.noreply.github.com>
License: MIT License
Project-URL: Homepage, https://github.com/ary5/tachibind
Project-URL: Repository, https://github.com/ary5/tachibind
Requires-Python: >=3.9
License-File: LICENSE
Requires-Dist: requests
Requires-Dist: beautifulsoup4
Requires-Dist: Pillow
Dynamic: license-file
